ecomment/cli.py
ecomment/convert.py
ecomment/strip.py
ecomment-0.1.3.dist-info/entry_points.txt
ecomment-0.1.3.dist-info/WHEEL
ecomment-0.1.3.dist-info/METADATA
ecomment-0.1.3.dist-info/RECORD
