Metadata-Version: 2.1
Name: ecomment
Version: 0.1.3
Summary: Comments want to be free.
Home-page: https://github.com/ecomment/ecomment
License: MIT
Keywords: comment,cli,tool,workflow
Author: Jeremiah England
Author-email: englandtuning@gmail.com
Requires-Python: >=3.8,<4.0
Classifier: License :: OSI Approved :: MIT License
Classifier: Programming Language :: Python :: 3
Classifier: Programming Language :: Python :: 3.10
Classifier: Programming Language :: Python :: 3.8
Classifier: Programming Language :: Python :: 3.9
Project-URL: Documentation, https://github.com/ecomment/ecomment/tree/master/README.md
Project-URL: Repository, https://github.com/ecomment/ecomment
